LICENSE.txt
MANIFEST.in
requirements.txt
setup.cfg
setup.py
lrutils/__init__.py
lrutils.egg-info/PKG-INFO
lrutils.egg-info/SOURCES.txt
lrutils.egg-info/dependency_links.txt
lrutils.egg-info/not-zip-safe
lrutils.egg-info/requires.txt
lrutils.egg-info/top_level.txt
lrutils/address/__init__.py
lrutils/address/address_utils.py
lrutils/audit/__init__.py
lrutils/errorhandler/__init__.py
lrutils/errorhandler/errorhandler_utils.py
lrutils/password/__init__.py
lrutils/password/password_utils.py
lrutils/templatefilters/__init__.py
lrutils/templatefilters/template_filters.py