Metadata-Version: 1.1
Name: lrutils
Version: 0.1.4
Summary: Utilities for LR Flask apps
Home-page: https://github.com/LandRegistry/lr-utils
Author: Land Registry
Author-email: paul.trelease@digital.landregistry.gov.uk
License: MIT
Download-URL: http://github.com/LandRegistry/lr-utils/tarball/alpha
Platform: any
Classifier: Development Status :: 3 - Alpha
Classifier: Environment :: Web Environment
Classifier: Programming Language :: Python :: 3.4
